api/__init__.py
api/app/__init__.py
api/app/api.py
api/app/config.py
api/app/main.py
api/app/schemas/__init__.py
api/app/schemas/health.py
api/app/schemas/predict.py
api/app/tests/__init__.py
api/app/tests/conftest.py
api/app/tests/test_api.py
regression_model/VERSION
regression_model/__init__.py
regression_model/config.yml
regression_model/pipeline.py
regression_model/predict.py
regression_model/train_pipeline.py
regression_model/config/__init__.py
regression_model/config/core.py
regression_model/datasets/__init__.py
regression_model/datasets/test.csv
regression_model/datasets/train.csv
regression_model/processing/__init__.py
regression_model/processing/data_manager.py
regression_model/processing/features.py
regression_model/processing/validation.py
regression_model/trained_models/__init__.py
regression_model/trained_models/regression_model_output_v0.0.6.pkl
sam_tid_regression_model-0.0.6.dist-info/METADATA
sam_tid_regression_model-0.0.6.dist-info/WHEEL
sam_tid_regression_model-0.0.6.dist-info/top_level.txt
sam_tid_regression_model-0.0.6.dist-info/RECORD
