Metadata-Version: 2.1
Name: sam-tid-regression-model
Version: 0.0.6
Summary: An example sales prediction regression model package from Train In Data.
Home-page: UNKNOWN
Author: Samuel Ajayi
Author-email: ajayisamuelofficial@gmail.com
License: BSD-3
Platform: UNKNOWN
Classifier: License :: OSI Approved :: MIT License
Classifier: Programming Language :: Python
Classifier: Programming Language :: Python :: 3
Classifier: Programming Language :: Python :: 3.6
Classifier: Programming Language :: Python :: 3.7
Classifier: Programming Language :: Python :: 3.8
Classifier: Programming Language :: Python :: 3.9
Classifier: Programming Language :: Python :: Implementation :: CPython
Classifier: Programming Language :: Python :: Implementation :: PyPy
Requires-Python: >=3.6.0
Requires-Dist: numpy (==1.19.2)
Requires-Dist: pandas (==1.1.5)
Requires-Dist: pydantic (==1.9.0)
Requires-Dist: scikit-learn (==0.24.2)
Requires-Dist: strictyaml (==1.6.1)
Requires-Dist: ruamel.yaml (==0.17.4)
Requires-Dist: feature-engine (==1.2.0)
Requires-Dist: joblib (==1.0.1)
